django_ga_context-0.1.0.dist-info/metadata.json
django_ga_context-0.1.0.dist-info/METADATA
django_ga_context-0.1.0.dist-info/WHEEL
django_ga_context-0.1.0.dist-info/DESCRIPTION.rst
django_ga_context-0.1.0.dist-info/RECORD
django_ga_context-0.1.0.dist-info/top_level.txt
gacontext/__init__.py
