Metadata-Version: 2.0
Name: django-ga-context
Version: 0.1.0
Summary: google analytics context processor
Home-page: UNKNOWN
Author: Anders Pearson
Author-email: anders@columbia.edu
License: BSD
Platform: any
